bandhic/__init__.py
bandhic/_conv2d.py
bandhic/_create.py
bandhic/_func.py
bandhic/_io.py
bandhic/_test_utils.py
bandhic/_ufunc.py
bandhic/bandhic.py
bandhic/utils/APA.py
bandhic/utils/HiCCUPS.py
bandhic/utils/HiCKRy.py
bandhic/utils/SCC.py
bandhic/utils/__init__.py
bandhic/utils/topdom.py
bandhic-0.2.0.dist-info/licenses/LICENSE
test/__init__.py
test/bandHiC_benchmark.py
test/bandhic_mask_row_test.py
test/bandhic_test.py
test/benchmark_sparse.py
test/topdom_benchmark.py
bandhic-0.2.0.dist-info/METADATA
bandhic-0.2.0.dist-info/WHEEL
bandhic-0.2.0.dist-info/top_level.txt
bandhic-0.2.0.dist-info/RECORD
