Metadata-Version: 2.4
Name: bandhic
Version: 0.2.0
Summary: A memory-efficient Python package for managing and analyzing Hi-C data down to sub-kilobase resolution
Author: Weibing Wang
Author-email: Weibing Wang <wangweibing@xidian.edu.cn>
License: MIT
Classifier: Programming Language :: Python :: 3
Classifier: License :: OSI Approved :: MIT License
Classifier: Operating System :: OS Independent
Requires-Python: >=3.11
License-File: LICENSE
Requires-Dist: numpy>=1.26
Requires-Dist: pandas>=2.3
Requires-Dist: scipy>=1.16
Requires-Dist: cooler>=0.10
Requires-Dist: joblib>=1.2
Requires-Dist: numba>=0.59
Dynamic: author
Dynamic: license-file
Dynamic: requires-python
